gdby-0.17.dist-info/DESCRIPTION.rst
gdby-0.17.dist-info/METADATA
gdby-0.17.dist-info/RECORD
gdby-0.17.dist-info/WHEEL
gdby-0.17.dist-info/entry_points.txt
gdby-0.17.dist-info/metadata.json
gdby-0.17.dist-info/top_level.txt
generate_yaml/__init__.py
generate_yaml/generate_yaml.py
