Metadata-Version: 2.0
Name: gdby
Version: 0.17
Summary: a tool for generating special db format yaml
Home-page: UNKNOWN
Author: sea
Author-email: sealevelnn@163.com
License: UNKNOWN
Platform: UNKNOWN
Requires-Dist: requests
